pyrai/__init__.py
pyrai/api.py
tests/__init__.py
tests/pyrai_test.py
pyrai-0.0.3.dist-info/LICENSE
pyrai-0.0.3.dist-info/METADATA
pyrai-0.0.3.dist-info/WHEEL
pyrai-0.0.3.dist-info/top_level.txt
pyrai-0.0.3.dist-info/RECORD
