Metadata-Version: 2.1
Name: pyrai
Version: 0.0.3
Summary: A Python library for the Routable AI API
Home-page: https://github.com/routable-ai/pyrai
Author: Routable AI
Author-email: eng@routable.ai
License: UNKNOWN
Platform: UNKNOWN
Classifier: Programming Language :: Python :: 3
Classifier: License :: OSI Approved :: MIT License
Classifier: Operating System :: OS Independent
Requires-Python: >=3.6
Requires-Dist: ipython
Requires-Dist: plotly
Requires-Dist: python-dateutil
Requires-Dist: pytimeparse
Requires-Dist: requests
